count_syllable.py
count_syllable-0.1.0.dist-info/METADATA
count_syllable-0.1.0.dist-info/WHEEL
count_syllable-0.1.0.dist-info/top_level.txt
count_syllable-0.1.0.dist-info/RECORD
