Metadata-Version: 2.1
Name: count-syllable
Version: 0.1.0
Summary: Count syllables in English
Home-page: https://github.com/ShinyaAkagiI/count_syllable
Author: Shinya Akagi
License: PSF
Requires-Dist: nltk
